prettypic/ColorGen/__init__.py
prettypic/__init__.py
prettypic-1.2.1.dist-info/METADATA
prettypic-1.2.1.dist-info/WHEEL
prettypic-1.2.1.dist-info/RECORD
