Metadata-Version: 2.1
Name: prettyPic
Version: 1.2.1
Summary: Takes a picture and finds the best color equality using machine learning. The use case this was built for was album cover backdrops, but others exist.
Home-page: https://github.com/msherburne/prettyPic
License: MIT
Keywords: image,pretty,python3,color
Author: msherburne
Author-email: mathieusherburne@outlook.com
Requires-Python: >=3.9,<4.0
Classifier: License :: OSI Approved :: MIT License
Classifier: Programming Language :: Python :: 3
Classifier: Programming Language :: Python :: 3.9
Classifier: Programming Language :: Python :: 3.10
Classifier: Programming Language :: Python :: 3.11
Requires-Dist: Pillow (>=10.0.0,<11.0.0)
Requires-Dist: numpy (>=1.25.2,<2.0.0)
Requires-Dist: pandas (>=2.0.3,<3.0.0)
Requires-Dist: pytest (>=7.4.0,<8.0.0)
Requires-Dist: scikit-learn (>=1.3.0,<2.0.0)
Project-URL: Documentation, https://github.com/msherburne/prettyPic
Project-URL: Repository, https://github.com/msherburne/prettyPic
